[
  {
    "Name": "Warszawa",
    "EnglishNames": [
      "Warsaw"
    ],
    "Voivodeship": "mazowieckie",
    "Population": 1777972
  },
  {
    "Name": "Kraków",
    "EnglishNames": [
      "Cracow",
      "Krakow"
    ],
    "Voivodeship": "małopolskie",
    "Population": 771069
  },
  {
    "Name": "Łódź",
    "EnglishNames": [
      "Lodz"
    ],
    "Voivodeship": "łódzkie",
    "Population": 685285
  },
  {
    "Name": "Wrocław",
    "EnglishNames": [
      "Wroclaw"
    ],
    "Voivodeship": "dolnośląskie",
    "Population": 640648
  },
  {
    "Name": "Poznań",
    "EnglishNames": [
      "Poznan"
    ],
    "Voivodeship": "wielkopolskie",
    "Population": 536438
  },
  {
    "Name": "Gdańsk",
    "EnglishNames": [
      "Gdansk"
    ],
    "Voivodeship": "pomorskie",
    "Population": 466631
  },
  {
    "Name": "Szczecin",
    "EnglishNames": [],
    "Voivodeship": "zachodniopomorskie",
    "Population": 402465
  },
  {
    "Name": "Bydgoszcz",
    "EnglishNames": [],
    "Voivodeship": "kujawsko-pomorskie",
    "Population": 350178
  },
  {
    "Name": "Lublin",
    "EnglishNames": [],
    "Voivodeship": "lubelskie",
    "Population": 339682
  },
  {
    "Name": "Białystok",
    "EnglishNames": [
      "Bialystok"
    ],
    "Voivodeship": "podlaskie",
    "Population": 297459
  },
  {
    "Name": "Katowice",
    "EnglishNames": [],
    "Voivodeship": "śląskie",
    "Population": 294510
  },
  {
    "Name": "Gdynia",
    "EnglishNames": [],
    "Voivodeship": "pomorskie",
    "Population": 246309
  },
  {
    "Name": "Częstochowa",
    "EnglishNames": [
      "Czestochowa"
    ],
    "Voivodeship": "śląskie",
    "Population": 222292
  },
  {
    "Name": "Radom",
    "EnglishNames": [],
    "Voivodeship": "mazowieckie",
    "Population": 213029
  },
  {
    "Name": "Toruń",
    "EnglishNames": [
      "Torun"
    ],
    "Voivodeship": "kujawsko-pomorskie",
    "Population": 202074
  },
  {
    "Name": "Sosnowiec",
    "EnglishNames": [],
    "Voivodeship": "śląskie",
    "Population": 202036
  },
  {
    "Name": "Kielce",
    "EnglishNames": [],
    "Voivodeship": "świętokrzyskie",
    "Population": 195774
  },
  {
    "Name": "Rzeszów",
    "EnglishNames": [
      "Rzeszow"
    ],
    "Voivodeship": "podkarpackie",
    "Population": 193883
  },
  {
    "Name": "Gliwice",
    "EnglishNames": [],
    "Voivodeship": "śląskie",
    "Population": 179806
  },
  {
    "Name": "Zabrze",
    "EnglishNames": [],
    "Voivodeship": "śląskie",
    "Population": 173374
  },
  {
    "Name": "Olsztyn",
    "EnglishNames": [],
    "Voivodeship": "warmińsko-mazurskie",
    "Population": 172362
  },
  {
    "Name": "Bielsko-Biała",
    "EnglishNames": [
      "Bielsko-Biala"
    ],
    "Voivodeship": "śląskie",
    "Population": 171259
  },
  {
    "Name": "Bytom",
    "EnglishNames": [],
    "Voivodeship": "śląskie",
    "Population": 166795
  },
  {
    "Name": "Zielona Góra",
    "EnglishNames": [
      "Zielona Gora"
    ],
    "Voivodeship": "lubuskie",
    "Population": 140297
  },
  {
    "Name": "Rybnik",
    "EnglishNames": [],
    "Voivodeship": "śląskie",
    "Population": 138696
  },
  {
    "Name": "Ruda Śląska",
    "EnglishNames": [
      "Ruda Slaska"
    ],
    "Voivodeship": "śląskie",
    "Population": 138000
  },
  {
    "Name": "Opole",
    "EnglishNames": [],
    "Voivodeship": "opolskie",
    "Population": 128137
  },
  {
    "Name": "Tychy",
    "EnglishNames": [],
    "Voivodeship": "śląskie",
    "Population": 127831
  },
  {
    "Name": "Gorzów Wielkopolski",
    "EnglishNames": [
      "Gorzow Wielkopolski"
    ],
    "Voivodeship": "lubuskie",
    "Population": 123921
  },
  {
    "Name": "Dąbrowa Górnicza",
    "EnglishNames": [
      "Dabrowa Gornicza"
    ],
    "Voivodeship": "śląskie",
    "Population": 120259
  },
  {
    "Name": "Elbląg",
    "EnglishNames": [
      "Elblag"
    ],
    "Voivodeship": "warmińsko-mazurskie",
    "Population": 120142
  },
  {
    "Name": "Płock",
    "EnglishNames": [
      "Plock"
    ],
    "Voivodeship": "mazowieckie",
    "Population": 120000
  },
  {
    "Name": "Wałbrzych",
    "EnglishNames": [
      "Walbrzych"
    ],
    "Voivodeship": "dolnośląskie",
    "Population": 112594
  },
  {
    "Name": "Włocławek",
    "EnglishNames": [
      "Wloclawek"
    ],
    "Voivodeship": "kujawsko-pomorskie",
    "Population": 110802
  },
  {
    "Name": "Tarnów",
    "EnglishNames": [
      "Tarnow"
    ],
    "Voivodeship": "małopolskie",
    "Population": 109062
  },
  {
    "Name": "Chorzów",
    "EnglishNames": [
      "Chorzow"
    ],
    "Voivodeship": "śląskie",
    "Population": 108434
  },
  {
    "Name": "Koszalin",
    "EnglishNames": [],
    "Voivodeship": "zachodniopomorskie",
    "Population": 107321
  },
  {
    "Name": "Kalisz",
    "EnglishNames": [],
    "Voivodeship": "wielkopolskie",
    "Population": 100975
  },
  {
    "Name": "Legnica",
    "EnglishNames": [],
    "Voivodeship": "dolnośląskie",
    "Population": 99752
  },
  {
    "Name": "Grudziądz",
    "EnglishNames": [
      "Grudziadz"
    ],
    "Voivodeship": "kujawsko-pomorskie",
    "Population": 95045
  },
  {
    "Name": "Jaworzno",
    "EnglishNames": [],
    "Voivodeship": "śląskie",
    "Population": 91563
  },
  {
    "Name": "Słupsk",
    "EnglishNames": [
      "Slupsk"
    ],
    "Voivodeship": "pomorskie",
    "Population": 91007
  },
  {
    "Name": "Jastrzębie-Zdrój",
    "EnglishNames": [
      "Jastrzebie-Zdroj"
    ],
    "Voivodeship": "śląskie",
    "Population": 89128
  },
  {
    "Name": "Nowy Sącz",
    "EnglishNames": [
      "Nowy Sacz"
    ],
    "Voivodeship": "małopolskie",
    "Population": 83896
  },
  {
    "Name": "Jelenia Góra",
    "EnglishNames": [
      "Jelenia Gora"
    ],
    "Voivodeship": "dolnośląskie",
    "Population": 79480
  },
  {
    "Name": "Siedlce",
    "EnglishNames": [],
    "Voivodeship": "mazowieckie",
    "Population": 77872
  },
  {
    "Name": "Mysłowice",
    "EnglishNames": [
      "Myslowice"
    ],
    "Voivodeship": "śląskie",
    "Population": 74586
  },
  {
    "Name": "Konin",
    "EnglishNames": [],
    "Voivodeship": "wielkopolskie",
    "Population": 74151
  },
  {
    "Name": "Piotrków Trybunalski",
    "EnglishNames": [
      "Piotrkow Trybunalski"
    ],
    "Voivodeship": "łódzkie",
    "Population": 73670
  },
  {
    "Name": "Piła",
    "EnglishNames": [
      "Pila"
    ],
    "Voivodeship": "wielkopolskie",
    "Population": 73398
  },
  {
    "Name": "Inowrocław",
    "EnglishNames": [
      "Inowroclaw"
    ],
    "Voivodeship": "kujawsko-pomorskie",
    "Population": 73114
  },
  {
    "Name": "Lubin",
    "EnglishNames": [],
    "Voivodeship": "dolnośląskie",
    "Population": 72581
  },
  {
    "Name": "Ostrów Wielkopolski",
    "EnglishNames": [
      "Ostrow Wielkopolski"
    ],
    "Voivodeship": "wielkopolskie",
    "Population": 72050
  },
  {
    "Name": "Suwałki",
    "EnglishNames": [
      "Suwalki"
    ],
    "Voivodeship": "podlaskie",
    "Population": 69827
  },
  {
    "Name": "Ostrowiec Świętokrzyski",
    "EnglishNames": [
      "Ostrowiec Swietokrzyski"
    ],
    "Voivodeship": "świętokrzyskie",
    "Population": 69051
  },
  {
    "Name": "Gniezno",
    "EnglishNames": [],
    "Voivodeship": "wielkopolskie",
    "Population": 68479
  },
  {
    "Name": "Stargard",
    "EnglishNames": [],
    "Voivodeship": "zachodniopomorskie",
    "Population": 67938
  },
  {
    "Name": "Głogów",
    "EnglishNames": [
      "Glogow"
    ],
    "Voivodeship": "dolnośląskie",
    "Population": 67615
  },
  {
    "Name": "Siemianowice Śląskie",
    "EnglishNames": [
      "Siemianowice Slaskie"
    ],
    "Voivodeship": "śląskie",
    "Population": 67154
  },
  {
    "Name": "Pabianice",
    "EnglishNames": [],
    "Voivodeship": "łódzkie",
    "Population": 65283
  },
  {
    "Name": "Leszno",
    "EnglishNames": [],
    "Voivodeship": "wielkopolskie",
    "Population": 63952
  },
  {
    "Name": "Zamość",
    "EnglishNames": [
      "Zamosc"
    ],
    "Voivodeship": "lubelskie",
    "Population": 63813
  },
  {
    "Name": "Łomża",
    "EnglishNames": [
      "Lomza"
    ],
    "Voivodeship": "podlaskie",
    "Population": 63000
  },
  {
    "Name": "Chełm",
    "EnglishNames": [
      "Chelm"
    ],
    "Voivodeship": "lubelskie",
    "Population": 62670
  },
  {
    "Name": "Tomaszów Mazowiecki",
    "EnglishNames": [
      "Tomaszow Mazowiecki"
    ],
    "Voivodeship": "łódzkie",
    "Population": 62649
  },
  {
    "Name": "Żory",
    "EnglishNames": [
      "Zory"
    ],
    "Voivodeship": "śląskie",
    "Population": 62456
  },
  {
    "Name": "Ełk",
    "EnglishNames": [
      "Elk"
    ],
    "Voivodeship": "warmińsko-mazurskie",
    "Population": 61928
  },
  {
    "Name": "Pruszków",
    "EnglishNames": [
      "Pruszkow"
    ],
    "Voivodeship": "mazowieckie",
    "Population": 61784
  },
  {
    "Name": "Tarnowskie Góry",
    "EnglishNames": [
      "Tarnowskie Gory"
    ],
    "Voivodeship": "śląskie",
    "Population": 61361
  },
  {
    "Name": "Przemyśl",
    "EnglishNames": [
      "Przemysl"
    ],
    "Voivodeship": "podkarpackie",
    "Population": 61251
  },
  {
    "Name": "Stalowa Wola",
    "EnglishNames": [],
    "Voivodeship": "podkarpackie",
    "Population": 61182
  },
  {
    "Name": "Kędzierzyn-Koźle",
    "EnglishNames": [
      "Kedzierzyn-Kozle"
    ],
    "Voivodeship": "opolskie",
    "Population": 61062
  },
  {
    "Name": "Mielec",
    "EnglishNames": [],
    "Voivodeship": "podkarpackie",
    "Population": 60478
  },
  {
    "Name": "Tczew",
    "EnglishNames": [],
    "Voivodeship": "pomorskie",
    "Population": 60279
  },
  {
    "Name": "Bełchatów",
    "EnglishNames": [
      "Belchatow"
    ],
    "Voivodeship": "łódzkie",
    "Population": 57432
  },
  {
    "Name": "Biała Podlaska",
    "EnglishNames": [
      "Biala Podlaska"
    ],
    "Voivodeship": "lubelskie",
    "Population": 57352
  },
  {
    "Name": "Świdnica",
    "EnglishNames": [
      "Swidnica"
    ],
    "Voivodeship": "dolnośląskie",
    "Population": 57310
  },
  {
    "Name": "Będzin",
    "EnglishNames": [
      "Bedzin"
    ],
    "Voivodeship": "śląskie",
    "Population": 56804
  },
  {
    "Name": "Zgierz",
    "EnglishNames": [],
    "Voivodeship": "łódzkie",
    "Population": 56529
  },
  {
    "Name": "Piekary Śląskie",
    "EnglishNames": [
      "Piekary Slaskie"
    ],
    "Voivodeship": "śląskie",
    "Population": 55299
  },
  {
    "Name": "Racibórz",
    "EnglishNames": [
      "Raciborz"
    ],
    "Voivodeship": "śląskie",
    "Population": 54882
  },
  {
    "Name": "Legionowo",
    "EnglishNames": [],
    "Voivodeship": "mazowieckie",
    "Population": 54066
  },
  {
    "Name": "Ostrołęka",
    "EnglishNames": [
      "Ostroleka"
    ],
    "Voivodeship": "mazowieckie",
    "Population": 52262
  },
  {
    "Name": "Świętochłowice",
    "EnglishNames": [
      "Swietochlowice"
    ],
    "Voivodeship": "śląskie",
    "Population": 50012
  },
  {
    "Name": "Wejherowo",
    "EnglishNames": [],
    "Voivodeship": "pomorskie",
    "Population": 49789
  },
  {
    "Name": "Zawiercie",
    "EnglishNames": [],
    "Voivodeship": "śląskie",
    "Population": 49567
  },
  {
    "Name": "Rumia",
    "EnglishNames": [],
    "Voivodeship": "pomorskie",
    "Population": 49031
  },
  {
    "Name": "Starachowice",
    "EnglishNames": [],
    "Voivodeship": "świętokrzyskie",
    "Population": 48965
  },
  {
    "Name": "Skierniewice",
    "EnglishNames": [],
    "Voivodeship": "łódzkie",
    "Population": 48178
  },
  {
    "Name": "Wodzisław Śląski",
    "EnglishNames": [
      "Wodzislaw Slaski"
    ],
    "Voivodeship": "śląskie",
    "Population": 48143
  },
  {
    "Name": "Piaseczno",
    "EnglishNames": [],
    "Voivodeship": "mazowieckie",
    "Population": 48119
  },
  {
    "Name": "Starogard Gdański",
    "EnglishNames": [
      "Starogard Gdanski"
    ],
    "Voivodeship": "pomorskie",
    "Population": 47776
  },
  {
    "Name": "Puławy",
    "EnglishNames": [
      "Pulawy"
    ],
    "Voivodeship": "lubelskie",
    "Population": 47774
  },
  {
    "Name": "Tarnobrzeg",
    "EnglishNames": [],
    "Voivodeship": "podkarpackie",
    "Population": 47047
  },
  {
    "Name": "Krosno",
    "EnglishNames": [],
    "Voivodeship": "podkarpackie",
    "Population": 46511
  },
  {
    "Name": "Kołobrzeg",
    "EnglishNames": [
      "Kolobrzeg"
    ],
    "Voivodeship": "zachodniopomorskie",
    "Population": 46367
  },
  {
    "Name": "Radomsko",
    "EnglishNames": [],
    "Voivodeship": "łódzkie",
    "Population": 46087
  },
  {
    "Name": "Dębica",
    "EnglishNames": [
      "Debica"
    ],
    "Voivodeship": "podkarpackie",
    "Population": 45817
  },
  {
    "Name": "Skarżysko-Kamienna",
    "EnglishNames": [
      "Skarzysko-Kamienna"
    ],
    "Voivodeship": "świętokrzyskie",
    "Population": 45358
  },
  {
    "Name": "Otwock",
    "EnglishNames": [],
    "Voivodeship": "mazowieckie",
    "Population": 44880
  }
]